skua/__init__.py
skua/files/__init__.py
skua/files/git.py
skua/pipelines/__init__.py
skua/preprocessors/__init__.py
skua/preprocessors/markdown.py
skua/render/__init__.py
tests/__init__.py
tests/files/__init__.py
tests/pipelines/__init__.py
tests/preprocessors/__init__.py
tests/render/__init__.py
skua-0.2.0.dist-info/LICENSE
skua-0.2.0.dist-info/METADATA
skua-0.2.0.dist-info/WHEEL
skua-0.2.0.dist-info/top_level.txt
skua-0.2.0.dist-info/RECORD
