Metadata-Version: 2.1
Name: skua
Version: 0.2.0
Summary: A static site generator.
Home-page: https://github.com/teymour-aldridge/skua
Author: Teymour Aldridge
Author-email: teymour.aldridge@icloud.com
License: UNKNOWN
Platform: UNKNOWN
Classifier: Programming Language :: Python :: 3
Classifier: License :: OSI Approved :: BSD License
Classifier: Operating System :: OS Independent
